fip/__init__.py
fip/__main__.py
fip/cli.py
fip/fip.py
fip-0.2.5.dist-info/DESCRIPTION.rst
fip-0.2.5.dist-info/METADATA
fip-0.2.5.dist-info/RECORD
fip-0.2.5.dist-info/WHEEL
fip-0.2.5.dist-info/entry_points.txt
fip-0.2.5.dist-info/metadata.json
fip-0.2.5.dist-info/top_level.txt
