Metadata-Version: 2.0
Name: fip
Version: 0.2.5
Summary: Read and extract current music information played on Fip            radio station.
Home-page: https://github.com/mattberjon/fip
Author: Matthieu Berjon
Author-email: matthieu@berjon.net
License: Apache Software License 2.0
Keywords: fip
Platform: UNKNOWN
Classifier: Development Status :: 2 - Pre-Alpha
Classifier: Intended Audience :: Developers
Classifier: License :: OSI Approved :: Apache Software License
Classifier: Natural Language :: English
Classifier: Programming Language :: Python :: 2
Classifier: Programming Language :: Python :: 2.7
Classifier: Programming Language :: Python :: 3
Classifier: Programming Language :: Python :: 3.3
Classifier: Programming Language :: Python :: 3.4
Classifier: Programming Language :: Python :: 3.5
Requires-Dist: Click (>=6.0)
Requires-Dist: requests (>=2.13.0)
